hyperpocket_crewai/__init__.py
hyperpocket_crewai/pocket_crewai.py
hyperpocket_crewai-0.5.7.dist-info/METADATA
hyperpocket_crewai-0.5.7.dist-info/WHEEL
hyperpocket_crewai-0.5.7.dist-info/RECORD
