Metadata-Version: 2.4
Name: hyperpocket-crewai
Version: 0.5.7
Requires-Python: >=3.10
Requires-Dist: crewai-tools>=0.32.1
Requires-Dist: crewai>=0.30.0
Requires-Dist: hyperpocket
